{
  "type": "FeatureCollection",
  "features": [
    {
      "type": "Feature",
      "geometry": {
        "type": "Point",
        "coordinates": [
          6.87,
          45.9225
        ]
      },
      "properties": {
        "code_station": "FR33120",
        "nom_station": "CHAMONIX",
        "nb_polluants": 5,
        "polluants": [
          {
            "polluant": "NO",
            "valeur_moyenne": 4.15,
            "valeur_max": 21.0,
            "valeur_min": 0.5,
            "nb_mesures": 24,
            "unite": "µg-m3",
            "date": "2026/02/04"
          },
          {
            "polluant": "NO2",
            "valeur_moyenne": 18.72,
            "valeur_max": 56.6,
            "valeur_min": 2.1,
            "nb_mesures": 24,
            "unite": "µg-m3",
            "date": "2026/02/04"
          },
          {
            "polluant": "NOX as NO2",
            "valeur_moyenne": 25.03,
            "valeur_max": 85.4,
            "valeur_min": 2.8,
            "nb_mesures": 24,
            "unite": "µg-m3",
            "date": "2026/02/04"
          },
          {
            "polluant": "O3",
            "valeur_moyenne": 51.8,
            "valeur_max": 80.0,
            "valeur_min": 3.8,
            "nb_mesures": 24,
            "unite": "µg-m3",
            "date": "2026/02/04"
          },
          {
            "polluant": "PM10",
            "valeur_moyenne": 14.98,
            "valeur_max": 45.7,
            "valeur_min": 2.1,
            "nb_mesures": 24,
            "unite": "µg-m3",
            "date": "2026/02/04"
          }
        ]
      }
    },
    {
      "type": "Feature",
      "geometry": {
        "type": "Point",
        "coordinates": [
          6.713611,
          45.92361
        ]
      },
      "properties": {
        "code_station": "FR33220",
        "nom_station": "PASSY",
        "nb_polluants": 6,
        "polluants": [
          {
            "polluant": "NO",
            "valeur_moyenne": 11.73,
            "valeur_max": 36.0,
            "valeur_min": 1.6,
            "nb_mesures": 24,
            "unite": "µg-m3",
            "date": "2026/02/04"
          },
          {
            "polluant": "NO2",
            "valeur_moyenne": 28.06,
            "valeur_max": 45.7,
            "valeur_min": 9.1,
            "nb_mesures": 24,
            "unite": "µg-m3",
            "date": "2026/02/04"
          },
          {
            "polluant": "NOX as NO2",
            "valeur_moyenne": 46.02,
            "valeur_max": 100.9,
            "valeur_min": 11.6,
            "nb_mesures": 24,
            "unite": "µg-m3",
            "date": "2026/02/04"
          },
          {
            "polluant": "O3",
            "valeur_moyenne": 17.65,
            "valeur_max": 48.3,
            "valeur_min": 0.4,
            "nb_mesures": 24,
            "unite": "µg-m3",
            "date": "2026/02/04"
          },
          {
            "polluant": "PM10",
            "valeur_moyenne": 37.62,
            "valeur_max": 67.9,
            "valeur_min": 8.6,
            "nb_mesures": 24,
            "unite": "µg-m3",
            "date": "2026/02/04"
          },
          {
            "polluant": "PM2.5",
            "valeur_moyenne": 22.02,
            "valeur_max": 52.9,
            "valeur_min": 5.7,
            "nb_mesures": 24,
            "unite": "µg-m3",
            "date": "2026/02/04"
          }
        ]
      }
    },
    {
      "type": "Feature",
      "geometry": {
        "type": "Point",
        "coordinates": [
          6.845833,
          45.907223
        ]
      },
      "properties": {
        "code_station": "FR33232",
        "nom_station": "BOSSONS",
        "nb_polluants": 4,
        "polluants": [
          {
            "polluant": "NO",
            "valeur_moyenne": 19.57,
            "valeur_max": 55.6,
            "valeur_min": -0.5,
            "nb_mesures": 24,
            "unite": "µg-m3",
            "date": "2026/02/04"
          },
          {
            "polluant": "NO2",
            "valeur_moyenne": 30.95,
            "valeur_max": 63.5,
            "valeur_min": 3.1,
            "nb_mesures": 24,
            "unite": "µg-m3",
            "date": "2026/02/04"
          },
          {
            "polluant": "NOX as NO2",
            "valeur_moyenne": 60.95,
            "valeur_max": 148.7,
            "valeur_min": 2.4,
            "nb_mesures": 24,
            "unite": "µg-m3",
            "date": "2026/02/04"
          },
          {
            "polluant": "PM10",
            "valeur_moyenne": 23.48,
            "valeur_max": 64.2,
            "valeur_min": 2.4,
            "nb_mesures": 24,
            "unite": "µg-m3",
            "date": "2026/02/04"
          }
        ]
      }
    }
  ]
}