{
  "type": "FeatureCollection",
  "features": [
    {
      "type": "Feature",
      "geometry": {
        "type": "Point",
        "coordinates": [
          6.845833,
          45.907223
        ]
      },
      "properties": {
        "name": "BOSSONS (FR33232)",
        "description": "<h3>BOSSONS</h3><p><strong>Code:</strong> FR33232</p><p><strong>4 polluants mesurés le 2026/02/04:</strong></p><table style='width:100%; border-collapse: collapse;'><tr style='border-bottom: 1px solid #ccc;'><th>Polluant</th><th>Moy.</th><th>Max</th><th>Min</th></tr><tr><td><strong>NO</strong></td><td>19.57 Âµg-m3</td><td>55.6</td><td>-0.5</td></tr><tr><td><strong>NO2</strong></td><td>30.95 Âµg-m3</td><td>63.5</td><td>3.1</td></tr><tr><td><strong>NOX as NO2</strong></td><td>60.95 Âµg-m3</td><td>148.7</td><td>2.4</td></tr><tr><td><strong>PM10</strong></td><td>23.48 Âµg-m3</td><td>64.2</td><td>2.4</td></tr></table>",
        "code_station": "FR33232",
        "nom_station": "BOSSONS",
        "nb_polluants": 4,
        "polluants": [
          {
            "polluant": "NO",
            "valeur_moyenne": 19.57,
            "valeur_max": 55.6,
            "valeur_min": -0.5,
            "nb_mesures": 24,
            "unite": "Âµg-m3",
            "date": "2026/02/04"
          },
          {
            "polluant": "NO2",
            "valeur_moyenne": 30.95,
            "valeur_max": 63.5,
            "valeur_min": 3.1,
            "nb_mesures": 24,
            "unite": "Âµg-m3",
            "date": "2026/02/04"
          },
          {
            "polluant": "NOX as NO2",
            "valeur_moyenne": 60.95,
            "valeur_max": 148.7,
            "valeur_min": 2.4,
            "nb_mesures": 24,
            "unite": "Âµg-m3",
            "date": "2026/02/04"
          },
          {
            "polluant": "PM10",
            "valeur_moyenne": 23.48,
            "valeur_max": 64.2,
            "valeur_min": 2.4,
            "nb_mesures": 24,
            "unite": "Âµg-m3",
            "date": "2026/02/04"
          }
        ]
      }
    }
  ]
}