{
  "type": "FeatureCollection",
  "features": [
    {
      "type": "Feature",
      "geometry": {
        "type": "Point",
        "coordinates": [
          6.713611,
          45.92361
        ]
      },
      "properties": {
        "name": "PASSY",
        "description": "<div style=\"font-family: Arial, sans-serif;\">\n<h3 style=\"margin:0 0 10px 0; color:#2c3e50;\">PASSY</h3>\n<p><strong>Code station:</strong> FR33220</p>\n<p><strong>Date:</strong> 2026/04/04</p>\n<table style=\"width:100%; border-collapse: collapse; font-size:13px;\">\n<thead>\n<tr style=\"background:#ecf0f1;\">\n<th style=\"padding:6px;\">Polluant</th>\n<th style=\"padding:6px;\">Moyenne</th>\n<th style=\"padding:6px;\">Max</th>\n<th style=\"padding:6px;\">Min</th>\n</tr>\n</thead>\n<tbody>\n\n<tr>\n<td style=\"padding:6px;\"><strong>NO</strong></td>\n<td style=\"padding:6px; text-align:center;\">1.68 µg-m3</td>\n<td style=\"padding:6px; text-align:center;\">9.6 µg-m3</td>\n<td style=\"padding:6px; text-align:center;\">0.8 µg-m3</td>\n</tr>\n\n<tr>\n<td style=\"padding:6px;\"><strong>NO2</strong></td>\n<td style=\"padding:6px; text-align:center;\">8.12 µg-m3</td>\n<td style=\"padding:6px; text-align:center;\">28.1 µg-m3</td>\n<td style=\"padding:6px; text-align:center;\">1.2 µg-m3</td>\n</tr>\n\n<tr>\n<td style=\"padding:6px;\"><strong>NOX as NO2</strong></td>\n<td style=\"padding:6px; text-align:center;\">10.69 µg-m3</td>\n<td style=\"padding:6px; text-align:center;\">42.8 µg-m3</td>\n<td style=\"padding:6px; text-align:center;\">2.3 µg-m3</td>\n</tr>\n\n<tr>\n<td style=\"padding:6px;\"><strong>O3</strong></td>\n<td style=\"padding:6px; text-align:center;\">61.85 µg-m3</td>\n<td style=\"padding:6px; text-align:center;\">97.6 µg-m3</td>\n<td style=\"padding:6px; text-align:center;\">17.3 µg-m3</td>\n</tr>\n\n<tr>\n<td style=\"padding:6px;\"><strong>PM10</strong></td>\n<td style=\"padding:6px; text-align:center;\">12.73 µg-m3</td>\n<td style=\"padding:6px; text-align:center;\">33.5 µg-m3</td>\n<td style=\"padding:6px; text-align:center;\">4.5 µg-m3</td>\n</tr>\n\n<tr>\n<td style=\"padding:6px;\"><strong>PM2.5</strong></td>\n<td style=\"padding:6px; text-align:center;\">8.66 µg-m3</td>\n<td style=\"padding:6px; text-align:center;\">20.1 µg-m3</td>\n<td style=\"padding:6px; text-align:center;\">1.0 µg-m3</td>\n</tr>\n\n</tbody>\n</table>\n<p style=\"font-size:11px; color:#7f8c8d;\">Source: ATMO Auvergne-Rhône-Alpes</p>\n</div>",
        "marker-color": "#e67e22",
        "marker-symbol": "circle"
      }
    },
    {
      "type": "Feature",
      "geometry": {
        "type": "Point",
        "coordinates": [
          6.845833,
          45.907223
        ]
      },
      "properties": {
        "name": "BOSSONS",
        "description": "<div style=\"font-family: Arial, sans-serif;\">\n<h3 style=\"margin:0 0 10px 0; color:#2c3e50;\">BOSSONS</h3>\n<p><strong>Code station:</strong> FR33232</p>\n<p><strong>Date:</strong> 2026/04/04</p>\n<table style=\"width:100%; border-collapse: collapse; font-size:13px;\">\n<thead>\n<tr style=\"background:#ecf0f1;\">\n<th style=\"padding:6px;\">Polluant</th>\n<th style=\"padding:6px;\">Moyenne</th>\n<th style=\"padding:6px;\">Max</th>\n<th style=\"padding:6px;\">Min</th>\n</tr>\n</thead>\n<tbody>\n\n<tr>\n<td style=\"padding:6px;\"><strong>NO</strong></td>\n<td style=\"padding:6px; text-align:center;\">17.91 µg-m3</td>\n<td style=\"padding:6px; text-align:center;\">83.3 µg-m3</td>\n<td style=\"padding:6px; text-align:center;\">-0.2 µg-m3</td>\n</tr>\n\n<tr>\n<td style=\"padding:6px;\"><strong>NO2</strong></td>\n<td style=\"padding:6px; text-align:center;\">26.17 µg-m3</td>\n<td style=\"padding:6px; text-align:center;\">68.8 µg-m3</td>\n<td style=\"padding:6px; text-align:center;\">8.0 µg-m3</td>\n</tr>\n\n<tr>\n<td style=\"padding:6px;\"><strong>NOX as NO2</strong></td>\n<td style=\"padding:6px; text-align:center;\">53.62 µg-m3</td>\n<td style=\"padding:6px; text-align:center;\">196.5 µg-m3</td>\n<td style=\"padding:6px; text-align:center;\">7.7 µg-m3</td>\n</tr>\n\n<tr>\n<td style=\"padding:6px;\"><strong>PM10</strong></td>\n<td style=\"padding:6px; text-align:center;\">11.59 µg-m3</td>\n<td style=\"padding:6px; text-align:center;\">24.2 µg-m3</td>\n<td style=\"padding:6px; text-align:center;\">5.2 µg-m3</td>\n</tr>\n\n</tbody>\n</table>\n<p style=\"font-size:11px; color:#7f8c8d;\">Source: ATMO Auvergne-Rhône-Alpes</p>\n</div>",
        "marker-color": "#e74c3c",
        "marker-symbol": "circle"
      }
    }
  ]
}