{
  "type": "FeatureCollection",
  "features": [
    {
      "type": "Feature",
      "geometry": {
        "type": "Point",
        "coordinates": [
          6.713611,
          45.92361
        ]
      },
      "properties": {
        "name": "PASSY",
        "description": "<div style=\"font-family: Arial, sans-serif;\">\n<h3 style=\"margin:0 0 10px 0; color:#2c3e50;\">PASSY</h3>\n<p><strong>Code station:</strong> FR33220</p>\n<p><strong>Date:</strong> 2026/04/09</p>\n<table style=\"width:100%; border-collapse: collapse; font-size:13px;\">\n<thead>\n<tr style=\"background:#ecf0f1;\">\n<th style=\"padding:6px;\">Polluant</th>\n<th style=\"padding:6px;\">Moyenne</th>\n<th style=\"padding:6px;\">Max</th>\n<th style=\"padding:6px;\">Min</th>\n</tr>\n</thead>\n<tbody>\n\n<tr>\n<td style=\"padding:6px;\"><strong>NO</strong></td>\n<td style=\"padding:6px; text-align:center;\">2.12 µg-m3</td>\n<td style=\"padding:6px; text-align:center;\">12.8 µg-m3</td>\n<td style=\"padding:6px; text-align:center;\">0.6 µg-m3</td>\n</tr>\n\n<tr>\n<td style=\"padding:6px;\"><strong>NO2</strong></td>\n<td style=\"padding:6px; text-align:center;\">7.61 µg-m3</td>\n<td style=\"padding:6px; text-align:center;\">32.6 µg-m3</td>\n<td style=\"padding:6px; text-align:center;\">1.1 µg-m3</td>\n</tr>\n\n<tr>\n<td style=\"padding:6px;\"><strong>NOX as NO2</strong></td>\n<td style=\"padding:6px; text-align:center;\">10.85 µg-m3</td>\n<td style=\"padding:6px; text-align:center;\">52.3 µg-m3</td>\n<td style=\"padding:6px; text-align:center;\">2.3 µg-m3</td>\n</tr>\n\n<tr>\n<td style=\"padding:6px;\"><strong>O3</strong></td>\n<td style=\"padding:6px; text-align:center;\">69.95 µg-m3</td>\n<td style=\"padding:6px; text-align:center;\">110.1 µg-m3</td>\n<td style=\"padding:6px; text-align:center;\">17.8 µg-m3</td>\n</tr>\n\n<tr>\n<td style=\"padding:6px;\"><strong>PM10</strong></td>\n<td style=\"padding:6px; text-align:center;\">17.99 µg-m3</td>\n<td style=\"padding:6px; text-align:center;\">82.0 µg-m3</td>\n<td style=\"padding:6px; text-align:center;\">7.3 µg-m3</td>\n</tr>\n\n<tr>\n<td style=\"padding:6px;\"><strong>PM2.5</strong></td>\n<td style=\"padding:6px; text-align:center;\">5.38 µg-m3</td>\n<td style=\"padding:6px; text-align:center;\">11.2 µg-m3</td>\n<td style=\"padding:6px; text-align:center;\">0.7 µg-m3</td>\n</tr>\n\n</tbody>\n</table>\n<p style=\"font-size:11px; color:#7f8c8d;\">Source: ATMO Auvergne-Rhône-Alpes</p>\n</div>",
        "marker-color": "#e74c3c",
        "marker-symbol": "circle"
      }
    },
    {
      "type": "Feature",
      "geometry": {
        "type": "Point",
        "coordinates": [
          6.845833,
          45.907223
        ]
      },
      "properties": {
        "name": "BOSSONS",
        "description": "<div style=\"font-family: Arial, sans-serif;\">\n<h3 style=\"margin:0 0 10px 0; color:#2c3e50;\">BOSSONS</h3>\n<p><strong>Code station:</strong> FR33232</p>\n<p><strong>Date:</strong> 2026/04/09</p>\n<table style=\"width:100%; border-collapse: collapse; font-size:13px;\">\n<thead>\n<tr style=\"background:#ecf0f1;\">\n<th style=\"padding:6px;\">Polluant</th>\n<th style=\"padding:6px;\">Moyenne</th>\n<th style=\"padding:6px;\">Max</th>\n<th style=\"padding:6px;\">Min</th>\n</tr>\n</thead>\n<tbody>\n\n<tr>\n<td style=\"padding:6px;\"><strong>NO</strong></td>\n<td style=\"padding:6px; text-align:center;\">15.82 µg-m3</td>\n<td style=\"padding:6px; text-align:center;\">77.2 µg-m3</td>\n<td style=\"padding:6px; text-align:center;\">0.2 µg-m3</td>\n</tr>\n\n<tr>\n<td style=\"padding:6px;\"><strong>NO2</strong></td>\n<td style=\"padding:6px; text-align:center;\">24.82 µg-m3</td>\n<td style=\"padding:6px; text-align:center;\">69.9 µg-m3</td>\n<td style=\"padding:6px; text-align:center;\">6.8 µg-m3</td>\n</tr>\n\n<tr>\n<td style=\"padding:6px;\"><strong>NOX as NO2</strong></td>\n<td style=\"padding:6px; text-align:center;\">49.06 µg-m3</td>\n<td style=\"padding:6px; text-align:center;\">188.3 µg-m3</td>\n<td style=\"padding:6px; text-align:center;\">7.4 µg-m3</td>\n</tr>\n\n<tr>\n<td style=\"padding:6px;\"><strong>PM10</strong></td>\n<td style=\"padding:6px; text-align:center;\">13.76 µg-m3</td>\n<td style=\"padding:6px; text-align:center;\">30.5 µg-m3</td>\n<td style=\"padding:6px; text-align:center;\">5.6 µg-m3</td>\n</tr>\n\n</tbody>\n</table>\n<p style=\"font-size:11px; color:#7f8c8d;\">Source: ATMO Auvergne-Rhône-Alpes</p>\n</div>",
        "marker-color": "#e74c3c",
        "marker-symbol": "circle"
      }
    }
  ]
}