{
  "type": "FeatureCollection",
  "features": [
    {
      "type": "Feature",
      "geometry": {
        "type": "Point",
        "coordinates": [
          6.713611,
          45.92361
        ]
      },
      "properties": {
        "name": "PASSY",
        "description": "<div style=\"font-family: Arial, sans-serif;\">\n<h3 style=\"margin:0 0 10px 0; color:#2c3e50;\">PASSY</h3>\n<p><strong>Code station:</strong> FR33220</p>\n<p><strong>Date:</strong> 2026/04/14</p>\n<table style=\"width:100%; border-collapse: collapse; font-size:13px;\">\n<thead>\n<tr style=\"background:#ecf0f1;\">\n<th style=\"padding:6px;\">Polluant</th>\n<th style=\"padding:6px;\">Moyenne</th>\n<th style=\"padding:6px;\">Max</th>\n<th style=\"padding:6px;\">Min</th>\n</tr>\n</thead>\n<tbody>\n\n<tr>\n<td style=\"padding:6px;\"><strong>NO</strong></td>\n<td style=\"padding:6px; text-align:center;\">1.26 µg-m3</td>\n<td style=\"padding:6px; text-align:center;\">2.5 µg-m3</td>\n<td style=\"padding:6px; text-align:center;\">0.6 µg-m3</td>\n</tr>\n\n<tr>\n<td style=\"padding:6px;\"><strong>NO2</strong></td>\n<td style=\"padding:6px; text-align:center;\">5.15 µg-m3</td>\n<td style=\"padding:6px; text-align:center;\">10.1 µg-m3</td>\n<td style=\"padding:6px; text-align:center;\">1.6 µg-m3</td>\n</tr>\n\n<tr>\n<td style=\"padding:6px;\"><strong>NOX as NO2</strong></td>\n<td style=\"padding:6px; text-align:center;\">7.06 µg-m3</td>\n<td style=\"padding:6px; text-align:center;\">12.6 µg-m3</td>\n<td style=\"padding:6px; text-align:center;\">2.5 µg-m3</td>\n</tr>\n\n<tr>\n<td style=\"padding:6px;\"><strong>O3</strong></td>\n<td style=\"padding:6px; text-align:center;\">37.49 µg-m3</td>\n<td style=\"padding:6px; text-align:center;\">49.8 µg-m3</td>\n<td style=\"padding:6px; text-align:center;\">17.3 µg-m3</td>\n</tr>\n\n<tr>\n<td style=\"padding:6px;\"><strong>PM10</strong></td>\n<td style=\"padding:6px; text-align:center;\">7.55 µg-m3</td>\n<td style=\"padding:6px; text-align:center;\">20.2 µg-m3</td>\n<td style=\"padding:6px; text-align:center;\">-1.2 µg-m3</td>\n</tr>\n\n<tr>\n<td style=\"padding:6px;\"><strong>PM2.5</strong></td>\n<td style=\"padding:6px; text-align:center;\">6.25 µg-m3</td>\n<td style=\"padding:6px; text-align:center;\">18.4 µg-m3</td>\n<td style=\"padding:6px; text-align:center;\">1.8 µg-m3</td>\n</tr>\n\n</tbody>\n</table>\n<p style=\"font-size:11px; color:#7f8c8d;\">Source: ATMO Auvergne-Rhône-Alpes</p>\n</div>",
        "marker-color": "#2ecc71",
        "marker-symbol": "circle"
      }
    },
    {
      "type": "Feature",
      "geometry": {
        "type": "Point",
        "coordinates": [
          6.845833,
          45.907223
        ]
      },
      "properties": {
        "name": "BOSSONS",
        "description": "<div style=\"font-family: Arial, sans-serif;\">\n<h3 style=\"margin:0 0 10px 0; color:#2c3e50;\">BOSSONS</h3>\n<p><strong>Code station:</strong> FR33232</p>\n<p><strong>Date:</strong> 2026/04/14</p>\n<table style=\"width:100%; border-collapse: collapse; font-size:13px;\">\n<thead>\n<tr style=\"background:#ecf0f1;\">\n<th style=\"padding:6px;\">Polluant</th>\n<th style=\"padding:6px;\">Moyenne</th>\n<th style=\"padding:6px;\">Max</th>\n<th style=\"padding:6px;\">Min</th>\n</tr>\n</thead>\n<tbody>\n\n<tr>\n<td style=\"padding:6px;\"><strong>NO</strong></td>\n<td style=\"padding:6px; text-align:center;\">14.0 µg-m3</td>\n<td style=\"padding:6px; text-align:center;\">60.3 µg-m3</td>\n<td style=\"padding:6px; text-align:center;\">-0.2 µg-m3</td>\n</tr>\n\n<tr>\n<td style=\"padding:6px;\"><strong>NO2</strong></td>\n<td style=\"padding:6px; text-align:center;\">14.26 µg-m3</td>\n<td style=\"padding:6px; text-align:center;\">45.2 µg-m3</td>\n<td style=\"padding:6px; text-align:center;\">2.8 µg-m3</td>\n</tr>\n\n<tr>\n<td style=\"padding:6px;\"><strong>NOX as NO2</strong></td>\n<td style=\"padding:6px; text-align:center;\">35.68 µg-m3</td>\n<td style=\"padding:6px; text-align:center;\">137.6 µg-m3</td>\n<td style=\"padding:6px; text-align:center;\">2.6 µg-m3</td>\n</tr>\n\n<tr>\n<td style=\"padding:6px;\"><strong>PM10</strong></td>\n<td style=\"padding:6px; text-align:center;\">8.25 µg-m3</td>\n<td style=\"padding:6px; text-align:center;\">16.3 µg-m3</td>\n<td style=\"padding:6px; text-align:center;\">1.5 µg-m3</td>\n</tr>\n\n</tbody>\n</table>\n<p style=\"font-size:11px; color:#7f8c8d;\">Source: ATMO Auvergne-Rhône-Alpes</p>\n</div>",
        "marker-color": "#e74c3c",
        "marker-symbol": "circle"
      }
    }
  ]
}