{
  "type": "FeatureCollection",
  "features": [
    {
      "type": "Feature",
      "geometry": {
        "type": "Point",
        "coordinates": [
          6.713611,
          45.92361
        ]
      },
      "properties": {
        "name": "PASSY",
        "description": "<div style=\"font-family: Arial, sans-serif;\">\n<h3 style=\"margin:0 0 10px 0; color:#2c3e50;\">PASSY</h3>\n<p><strong>Code station:</strong> FR33220</p>\n<p><strong>Date:</strong> 2026/04/05</p>\n<table style=\"width:100%; border-collapse: collapse; font-size:13px;\">\n<thead>\n<tr style=\"background:#ecf0f1;\">\n<th style=\"padding:6px;\">Polluant</th>\n<th style=\"padding:6px;\">Moyenne</th>\n<th style=\"padding:6px;\">Max</th>\n<th style=\"padding:6px;\">Min</th>\n</tr>\n</thead>\n<tbody>\n\n<tr>\n<td style=\"padding:6px;\"><strong>NO</strong></td>\n<td style=\"padding:6px; text-align:center;\">1.27 µg-m3</td>\n<td style=\"padding:6px; text-align:center;\">6.0 µg-m3</td>\n<td style=\"padding:6px; text-align:center;\">0.6 µg-m3</td>\n</tr>\n\n<tr>\n<td style=\"padding:6px;\"><strong>NO2</strong></td>\n<td style=\"padding:6px; text-align:center;\">4.17 µg-m3</td>\n<td style=\"padding:6px; text-align:center;\">16.1 µg-m3</td>\n<td style=\"padding:6px; text-align:center;\">0.1 µg-m3</td>\n</tr>\n\n<tr>\n<td style=\"padding:6px;\"><strong>NOX as NO2</strong></td>\n<td style=\"padding:6px; text-align:center;\">6.08 µg-m3</td>\n<td style=\"padding:6px; text-align:center;\">25.2 µg-m3</td>\n<td style=\"padding:6px; text-align:center;\">1.3 µg-m3</td>\n</tr>\n\n<tr>\n<td style=\"padding:6px;\"><strong>O3</strong></td>\n<td style=\"padding:6px; text-align:center;\">65.65 µg-m3</td>\n<td style=\"padding:6px; text-align:center;\">88.4 µg-m3</td>\n<td style=\"padding:6px; text-align:center;\">39.5 µg-m3</td>\n</tr>\n\n<tr>\n<td style=\"padding:6px;\"><strong>PM10</strong></td>\n<td style=\"padding:6px; text-align:center;\">7.98 µg-m3</td>\n<td style=\"padding:6px; text-align:center;\">15.9 µg-m3</td>\n<td style=\"padding:6px; text-align:center;\">3.5 µg-m3</td>\n</tr>\n\n<tr>\n<td style=\"padding:6px;\"><strong>PM2.5</strong></td>\n<td style=\"padding:6px; text-align:center;\">5.23 µg-m3</td>\n<td style=\"padding:6px; text-align:center;\">11.4 µg-m3</td>\n<td style=\"padding:6px; text-align:center;\">1.2 µg-m3</td>\n</tr>\n\n</tbody>\n</table>\n<p style=\"font-size:11px; color:#7f8c8d;\">Source: ATMO Auvergne-Rhône-Alpes</p>\n</div>",
        "marker-color": "#f1c40f",
        "marker-symbol": "circle"
      }
    },
    {
      "type": "Feature",
      "geometry": {
        "type": "Point",
        "coordinates": [
          6.845833,
          45.907223
        ]
      },
      "properties": {
        "name": "BOSSONS",
        "description": "<div style=\"font-family: Arial, sans-serif;\">\n<h3 style=\"margin:0 0 10px 0; color:#2c3e50;\">BOSSONS</h3>\n<p><strong>Code station:</strong> FR33232</p>\n<p><strong>Date:</strong> 2026/04/05</p>\n<table style=\"width:100%; border-collapse: collapse; font-size:13px;\">\n<thead>\n<tr style=\"background:#ecf0f1;\">\n<th style=\"padding:6px;\">Polluant</th>\n<th style=\"padding:6px;\">Moyenne</th>\n<th style=\"padding:6px;\">Max</th>\n<th style=\"padding:6px;\">Min</th>\n</tr>\n</thead>\n<tbody>\n\n<tr>\n<td style=\"padding:6px;\"><strong>NO</strong></td>\n<td style=\"padding:6px; text-align:center;\">12.7 µg-m3</td>\n<td style=\"padding:6px; text-align:center;\">50.4 µg-m3</td>\n<td style=\"padding:6px; text-align:center;\">0.0 µg-m3</td>\n</tr>\n\n<tr>\n<td style=\"padding:6px;\"><strong>NO2</strong></td>\n<td style=\"padding:6px; text-align:center;\">20.27 µg-m3</td>\n<td style=\"padding:6px; text-align:center;\">52.1 µg-m3</td>\n<td style=\"padding:6px; text-align:center;\">7.3 µg-m3</td>\n</tr>\n\n<tr>\n<td style=\"padding:6px;\"><strong>NOX as NO2</strong></td>\n<td style=\"padding:6px; text-align:center;\">39.7 µg-m3</td>\n<td style=\"padding:6px; text-align:center;\">129.4 µg-m3</td>\n<td style=\"padding:6px; text-align:center;\">8.1 µg-m3</td>\n</tr>\n\n<tr>\n<td style=\"padding:6px;\"><strong>PM10</strong></td>\n<td style=\"padding:6px; text-align:center;\">11.63 µg-m3</td>\n<td style=\"padding:6px; text-align:center;\">20.9 µg-m3</td>\n<td style=\"padding:6px; text-align:center;\">6.5 µg-m3</td>\n</tr>\n\n</tbody>\n</table>\n<p style=\"font-size:11px; color:#7f8c8d;\">Source: ATMO Auvergne-Rhône-Alpes</p>\n</div>",
        "marker-color": "#e74c3c",
        "marker-symbol": "circle"
      }
    }
  ]
}